check_graph/__init__.py
check_graph-1.0.2.dist-info/LICENSE
check_graph-1.0.2.dist-info/METADATA
check_graph-1.0.2.dist-info/WHEEL
check_graph-1.0.2.dist-info/top_level.txt
check_graph-1.0.2.dist-info/RECORD
