Metadata-Version: 2.1
Name: check-graph
Version: 1.0.2
Summary: This package is for graph classes recognisation.
Home-page: https://github.com/yatin2410/Graph_Classes
Author: Yatin Patel
Author-email: yatinpatel.gt@gmail.com
License: UNKNOWN
Platform: UNKNOWN
Classifier: Programming Language :: Python :: 3
Classifier: Operating System :: OS Independent
